flexstack/__init__.py
flexstack/flexstackapi.py
flexstack-0.1.1.dist-info/METADATA
flexstack-0.1.1.dist-info/WHEEL
flexstack-0.1.1.dist-info/top_level.txt
flexstack-0.1.1.dist-info/RECORD
