Metadata-Version: 2.1
Name: flexstack
Version: 0.1.1
Summary: API for FlexStack AI - a decentralized AI.
Author: FlexStack AI
Author-email: system@flexstack.ai
Classifier: Programming Language :: Python :: 3
Classifier: License :: OSI Approved :: Apache Software License
Classifier: Operating System :: OS Independent
Requires-Python: >=3.7
